MANIFEST.in
README.md
requirements.txt
setup.cfg
setup.py
iterpert/__init__.py
iterpert/data_pert.py
iterpert/iterpert.py
iterpert/nets_pert.py
iterpert/utils.py
iterpert/version.py
iterpert.egg-info/PKG-INFO
iterpert.egg-info/SOURCES.txt
iterpert.egg-info/dependency_links.txt
iterpert.egg-info/not-zip-safe
iterpert.egg-info/requires.txt
iterpert.egg-info/top_level.txt
iterpert/bmdal/__init__.py
iterpert/bmdal/algorithms.py
iterpert/bmdal/feature_data.py
iterpert/bmdal/feature_maps.py
iterpert/bmdal/features.py
iterpert/bmdal/layer_features.py
iterpert/bmdal/selection.py
iterpert/bmdal/utils.py
iterpert/gears/__init__.py
iterpert/gears/data_utils.py
iterpert/gears/gears.py
iterpert/gears/inference.py
iterpert/gears/model.py
iterpert/gears/pertdata.py
iterpert/gears/utils.py
iterpert/gears/version.py
iterpert/query_strategies/__init__.py
iterpert/query_strategies/kernel_based_active_learning.py
iterpert/query_strategies/kmeans_sampling.py
iterpert/query_strategies/strategy.py
iterpert/query_strategies/typiclust.py