Metadata-Version: 2.1
Name: iterpert
Version: 0.0.2
Summary: IterPert
Home-page: https://github.com/genentech/iterpert
Author: IterPert team
License: XXX
Platform: UNKNOWN
